abfn/__init__.py
abfn/abfn.py
abfn/character_ranges.py
abfn/configuration.py
abfn-0.0.7.dist-info/METADATA
abfn-0.0.7.dist-info/WHEEL
abfn-0.0.7.dist-info/top_level.txt
abfn-0.0.7.dist-info/RECORD
