Metadata-Version: 2.1
Name: abfn
Version: 0.0.7
Summary: ABFN rules for text filtering
Home-page: UNKNOWN
Author: Shubham Randive
License: UNKNOWN
Platform: UNKNOWN
Classifier: Programming Language :: Python :: 3
Classifier: License :: OSI Approved :: MIT License
Classifier: Operating System :: OS Independent
Requires-Python: >=3.6
